arato_proxy/__init__.py
arato_proxy/__main__.py
arato_proxy/cli.py
arato_proxy/config.yaml
arato_proxy/custom_callbacks.py
arato_proxy-0.3.1.dist-info/METADATA
arato_proxy-0.3.1.dist-info/WHEEL
arato_proxy-0.3.1.dist-info/entry_points.txt
arato_proxy-0.3.1.dist-info/licenses/LICENSE
arato_proxy-0.3.1.dist-info/RECORD
