Metadata-Version: 2.4
Name: arato-proxy
Version: 0.3.1
Summary: LiteLLM proxy for Arato logs
Project-URL: Homepage, https://github.com/AratoAi/litellm-proxy
Project-URL: Documentation, https://github.com/AratoAi/litellm-proxy#readme
Project-URL: Repository, https://github.com/AratoAi/litellm-proxy
Project-URL: Issues, https://github.com/AratoAi/litellm-proxy/issues
Author-email: Arato <dev@arato.com>
License: MIT
License-File: LICENSE
Keywords: arato,litellm,llm,logging,openai,proxy
Classifier: Development Status :: 4 - Beta
Classifier: Intended Audience :: Developers
Classifier: License :: OSI Approved :: MIT License
Classifier: Programming Language :: Python :: 3
Classifier: Programming Language :: Python :: 3.8
Classifier: Programming Language :: Python :: 3.9
Classifier: Programming Language :: Python :: 3.10
Classifier: Programming Language :: Python :: 3.11
Classifier: Programming Language :: Python :: 3.12
Classifier: Topic :: Internet :: WWW/HTTP :: HTTP Servers
Classifier: Topic :: Software Development :: Libraries :: Python Modules
Requires-Python: >=3.8
Requires-Dist: fastapi
Requires-Dist: litellm[proxy]
Requires-Dist: python-dotenv
Requires-Dist: requests
Requires-Dist: uvicorn
